shrinky/__init__.py
shrinky/__main__.py
shrinky-0.0.9.dist-info/METADATA
shrinky-0.0.9.dist-info/WHEEL
shrinky-0.0.9.dist-info/entry_points.txt
shrinky-0.0.9.dist-info/RECORD
