Metadata-Version: 2.4
Name: shrinky
Version: 0.0.9
Summary: Shrinks images in the way I want
Author-email: James Hogkinson <james@terminaloutcomes.com>
License: MIT
Requires-Python: <4.0,>=3.12
Requires-Dist: click>=8.3.1
Requires-Dist: loguru>=0.7.3
Requires-Dist: pillow-avif-plugin>=1.5.2
Requires-Dist: pillow-heif>=1.1.1
Requires-Dist: pillow>=12.1.0
